[
    {
        "name": "Lower-division: A. Select one of the following series:",
        "child": [
            {
                "name": "Group 1",
                "child":[
                    "I&C SCI 31",
                    "I&C SCI 32",
                    "I&C SCI 33"
                ]
            },
            {
                "name": "Group 2",
                "child": [
                    "I&C SCI 32A",
                    "I&C SCI 33"
                ]
            }  
        ]
    },
    {
        "name": "Lower Division: B. Complete:",
        "child": [
            {
                "name": "",
                "child": [
                    "I&C SCI 45C",
                    "I&C SCI 46",
                    "I&C SCI 51",
                    "I&C SCI 60",
                    "I&C SCI 61",
                    "I&C SCI 62",
                    "IN4MATX 43",
                    "MATH 2A",
                    "MATH 2B",
                    [
                        "I&C SCI 6N",
                        "MATH 3A"
                    ],
                    "I&C SCI 6B",
                    "I&C SCI 6D",
                    "STATS 67",
                    "PHYSICS 3A",
                    [
                        "FLM&MDA 85A",
                        "FLM&MDA 85C"
                    ]
                ]
            }
        ]
    },
    {
        "name": "Upper-division",
        "child": [
            {
                "name": "A. Computer Game Science Core Requirements",
                "child": [
                    "COMPSCI 171",
                    "I&C SCI 161",
                    "I&C SCI 162",
                    "I&C SCI 167",
                    "I&C SCI 168",
                    "I&C SCI 169A",
                    "I&C SCI 169B"
                ]
            },
            {
                "name": "And select two of the following:",
                "child": [
                    "COMPSCI 112",
                    "I&C SCI 163",
                    "I&C SCI 166"
                ]
            },
            {
                "name": "B. Select two of the following:",
                "child": [
                    "COMPSCI 122A",
                    "COMPSCI 132",
                    "COMPSCI 143A",
                    "COMPSCI 152",
                    "IN4MATX 113",
                    "IN4MATX 121",
                    "IN4MATX 131"
                ]
            },
            {
                "name": "C. CGS Elective Courses:\nFive additional courses:\n1. Two courses from A-C.\n2. Three courses must be in the same Bren ICS track.",
                "child": []
            }
        ]
    },
    {
        "name": "Bren ICS Tracks:",
        "child": [
            {
                "name": "Algorithms",
                "child": [
                    "COMPSCI 161",
                    "COMPSCI 162",
                    "COMPSCI 163",
                    "COMPSCI 164",
                    "COMPSCI 165"
                ]
            },
            {
                "name": "Artificial Intelligence",
                "child": [
                    "COMPSCI 171",
                    "COMPSCI 175",
                    "COMPSCI 177",
                    "COMPSCI 178",
                    "COMPSCI 179"
                ]
            },
            {
                "name": "Computational Biology",
                "child": [
                    "COMPSCI 183",
                    "COMPSCI 184A",
                    "COMPSCI 184C"
                ]
            },
            {
                "name": "Computer Graphics and Vision",
                "child": [
                    "COMPSCI 111",
                    "COMPSCI 112",
                    "COMPSCI 114",
                    "COMPSCI 116",
                    "COMPSCI 117"
                ]
            },
            {
                "name": "Computer Networks",
                "child": [
                    "COMPSCI 131",
                    "COMPSCI 132",
                    "COMPSCI 133",
                    "COMPSCI 134",
                    [
                        "COMPSCI 137",
                        "IN4MATX 124"
                    ]
                ]
            },
            {
                "name": "Databases",
                "child": [
                    [
                        "COMPSCI 121",
                        "IN4MATX 141"
                    ],
                    "COMPSCI 122A",
                    "COMPSCI 122B",
                    "COMPSCI 125"
                ]
            },
            {
                "name": "Hardware",
                "child": [
                    "COMPSCI 145",
                    "COMPSCI 151",
                    "COMPSCI 153",
                    "COMPSCI 154"
                ]
            },
            {
                "name": "Human-Computer Interaction",
                "child": [
                    "IN4MATX 131",
                    "IN4MATX 132",
                    "IN4MATX 133",
                    "IN4MATX 134"
                ]
            },
            {
                "name": "Operating Systems",
                "child": [
                    "COMPSCI 143A",
                    "COMPSCI 143B",
                    "COMPSCI 146"
                ]
            },
            {
                "name": "Programming Languages and Compilers",
                "child": [
                    "IN4MATX 101",
                    "IN4MATX 102",
                    "COMPSCI 142A",
                    "COMPSCI 142B"
                ]
            },
            {
                "name": "Social and Organizational Computing",
                "child": [
                    "IN4MATX 151",
                    "IN4MATX 153",
                    "IN4MATX 161",
                    "IN4MATX 162W",
                    "IN4MATX 163",
                    "IN4MATX 171"
                ]
            },
            {
                "name": "Software Engineering",
                "child": [
                    "IN4MATX 113",
                    "IN4MATX 115",
                    "IN4MATX 117",
                    "IN4MATX 121",
                    "IN4MATX 122",
                    "IN4MATX 124"
                ]
            }
        ]
    },
    {
        "name": "Non-Track Courses (some of these courses have prerequisites that are not part of the CGS major):",
        "child": [
            {
                "name": "Computer Game Science",
                "child": [
                    "I&C SCI 162",
                    "I&C SCI 163",
                    "I&C SCI 166"
                ]
            },
            {
                "name": "Business Management",
                "child": [
                    "MGMT 101",
                    "MGMT 102",
                    "MGMT 105",
                    "MGMT 154",
                    "MGMT 155"
                ]
            },
            {
                "name": "Cognitive Science",
                "child": [
                    "PSYCH 130A",
                    "PSYCH 131A",
                    "PSYCH 131B",
                    "PSYCH 135M",
                    "PSYCH 140C" 
                ]
            },
            {
                "name": "Mathematics",
                "child": [
                    "MATH 112A",
                    "MATH 112B",
                    "MATH 112C",
                    "MATH 115",
                    "MATH 121A",
                    "MATH 121B"
                ]
            },
            {
                "name": "Film and Media Studies",
                "child": [
                    "FLM&MDA 113",
                    "FLM&MDA 114",
                    "FLM&MDA 117A",
                    "FLM&MDA 144"
                ]
            }

        ]
    }
]